<workunit schemaName="master_tblvoluntarywork">
    <invokers>
        <invoker type="master_tblvoluntarywork:create" caption="New Voluntary Work" action="create" target="popup" role="MASTER"/>
        <invoker type="master_tblvoluntarywork:open" caption="Voluntary Work" action="open" target="popup" role="MASTER"/>
        <invoker type="formActions" caption="Approve" action="approve" 
                 visibleWhen="#{allowApprove==true}"/>
    </invokers>
    <code class="tagabukid.hrmis.appointment.models.MasterPDSVoluntaryWorkModel"/>
    <pages>
        <page template="tagabukid.hrmis.appointment.views.MasterPDSVoluntaryWorkView"/>
    </pages>
</workunit>
